{
    "key": "group_693ab51a8e4db",
    "title": "Case Studies",
    "fields": [
        {
            "key": "field_693ab51a87428",
            "label": "Hero",
            "name": "",
            "aria-label": "",
            "type": "tab",
            "instructions": "",
            "required": 0,
            "conditional_logic": 0,
            "wrapper": {
                "width": "",
                "class": "",
                "id": ""
            },
            "placement": "top",
            "endpoint": 0,
            "selected": 0
        },
        {
            "key": "field_693ab52a87429",
            "label": "casestudies_hero_bg_type",
            "name": "casestudies_hero_bg_type",
            "aria-label": "",
            "type": "select",
            "instructions": "",
            "required": 0,
            "conditional_logic": 0,
            "wrapper": {
                "width": "",
                "class": "",
                "id": ""
            },
            "choices": {
                "none": "none",
                "image": "image",
                "video": "video"
            },
            "default_value": false,
            "return_format": "value",
            "multiple": 0,
            "allow_null": 0,
            "allow_in_bindings": 0,
            "ui": 0,
            "ajax": 0,
            "placeholder": "",
            "create_options": 0,
            "save_options": 0
        },
        {
            "key": "field_693ab53a8742a",
            "label": "casestudies_hero_video",
            "name": "casestudies_hero_video",
            "aria-label": "",
            "type": "file",
            "instructions": "",
            "required": 0,
            "conditional_logic": [
                [
                    {
                        "field": "field_693ab52a87429",
                        "operator": "==contains",
                        "value": "video"
                    }
                ]
            ],
            "wrapper": {
                "width": "",
                "class": "",
                "id": ""
            },
            "return_format": "array",
            "library": "all",
            "min_size": "",
            "max_size": "",
            "mime_types": "",
            "allow_in_bindings": 0
        },
        {
            "key": "field_693ab5758742b",
            "label": "casestudies_hero_image",
            "name": "casestudies_hero_image",
            "aria-label": "",
            "type": "image",
            "instructions": "",
            "required": 0,
            "conditional_logic": [
                [
                    {
                        "field": "field_693ab52a87429",
                        "operator": "==contains",
                        "value": "image"
                    }
                ]
            ],
            "wrapper": {
                "width": "",
                "class": "",
                "id": ""
            },
            "return_format": "array",
            "library": "all",
            "min_width": "",
            "min_height": "",
            "min_size": "",
            "max_width": "",
            "max_height": "",
            "max_size": "",
            "mime_types": "",
            "allow_in_bindings": 0,
            "preview_size": "medium"
        },
        {
            "key": "field_693ab5808742c",
            "label": "casestudies_hero_label",
            "name": "casestudies_hero_label",
            "aria-label": "",
            "type": "text",
            "instructions": "",
            "required": 0,
            "conditional_logic": 0,
            "wrapper": {
                "width": "",
                "class": "",
                "id": ""
            },
            "default_value": "",
            "maxlength": "",
            "allow_in_bindings": 0,
            "placeholder": "",
            "prepend": "",
            "append": ""
        },
        {
            "key": "field_693ab5878742d",
            "label": "casestudies_hero_heading",
            "name": "casestudies_hero_heading",
            "aria-label": "",
            "type": "wysiwyg",
            "instructions": "",
            "required": 0,
            "conditional_logic": 0,
            "wrapper": {
                "width": "",
                "class": "",
                "id": ""
            },
            "default_value": "",
            "allow_in_bindings": 0,
            "tabs": "all",
            "toolbar": "full",
            "media_upload": 1,
            "delay": 0
        },
        {
            "key": "field_693ab5918742e",
            "label": "casestudies_hero_subheading",
            "name": "casestudies_hero_subheading",
            "aria-label": "",
            "type": "wysiwyg",
            "instructions": "",
            "required": 0,
            "conditional_logic": 0,
            "wrapper": {
                "width": "",
                "class": "",
                "id": ""
            },
            "default_value": "",
            "allow_in_bindings": 0,
            "tabs": "all",
            "toolbar": "full",
            "media_upload": 1,
            "delay": 0
        },
        {
            "key": "field_693ab59a8742f",
            "label": "casestudies_hero_button_text",
            "name": "casestudies_hero_button_text",
            "aria-label": "",
            "type": "text",
            "instructions": "",
            "required": 0,
            "conditional_logic": 0,
            "wrapper": {
                "width": "",
                "class": "",
                "id": ""
            },
            "default_value": "",
            "maxlength": "",
            "allow_in_bindings": 0,
            "placeholder": "",
            "prepend": "",
            "append": ""
        },
        {
            "key": "field_693ab5a387430",
            "label": "casestudies_hero_button_link",
            "name": "casestudies_hero_button_link",
            "aria-label": "",
            "type": "link",
            "instructions": "",
            "required": 0,
            "conditional_logic": 0,
            "wrapper": {
                "width": "",
                "class": "",
                "id": ""
            },
            "return_format": "array",
            "allow_in_bindings": 0
        },
        {
            "key": "field_693ab651dc14e",
            "label": "Intro",
            "name": "",
            "aria-label": "",
            "type": "tab",
            "instructions": "",
            "required": 0,
            "conditional_logic": 0,
            "wrapper": {
                "width": "",
                "class": "",
                "id": ""
            },
            "placement": "top",
            "endpoint": 0,
            "selected": 0
        },
        {
            "key": "field_693ab659dc14f",
            "label": "casestudies_intro_label",
            "name": "casestudies_intro_label",
            "aria-label": "",
            "type": "text",
            "instructions": "",
            "required": 0,
            "conditional_logic": 0,
            "wrapper": {
                "width": "",
                "class": "",
                "id": ""
            },
            "default_value": "",
            "maxlength": "",
            "allow_in_bindings": 0,
            "placeholder": "",
            "prepend": "",
            "append": ""
        },
        {
            "key": "field_693ab65fdc150",
            "label": "casestudies_intro_heading",
            "name": "casestudies_intro_heading",
            "aria-label": "",
            "type": "wysiwyg",
            "instructions": "",
            "required": 0,
            "conditional_logic": 0,
            "wrapper": {
                "width": "",
                "class": "",
                "id": ""
            },
            "default_value": "",
            "allow_in_bindings": 0,
            "tabs": "all",
            "toolbar": "full",
            "media_upload": 1,
            "delay": 0
        },
        {
            "key": "field_693ab667dc151",
            "label": "casestudies_intro_text",
            "name": "casestudies_intro_text",
            "aria-label": "",
            "type": "wysiwyg",
            "instructions": "",
            "required": 0,
            "conditional_logic": 0,
            "wrapper": {
                "width": "",
                "class": "",
                "id": ""
            },
            "default_value": "",
            "allow_in_bindings": 0,
            "tabs": "all",
            "toolbar": "full",
            "media_upload": 1,
            "delay": 0
        },
        {
            "key": "field_693ab678dc152",
            "label": "Stats",
            "name": "",
            "aria-label": "",
            "type": "tab",
            "instructions": "",
            "required": 0,
            "conditional_logic": 0,
            "wrapper": {
                "width": "",
                "class": "",
                "id": ""
            },
            "placement": "top",
            "endpoint": 0,
            "selected": 0
        },
        {
            "key": "field_693ab6f1dc153",
            "label": "casestudies_stats",
            "name": "casestudies_stats",
            "aria-label": "",
            "type": "repeater",
            "instructions": "",
            "required": 0,
            "conditional_logic": 0,
            "wrapper": {
                "width": "",
                "class": "",
                "id": ""
            },
            "layout": "table",
            "pagination": 0,
            "min": 0,
            "max": 0,
            "collapsed": "",
            "button_label": "Add Row",
            "rows_per_page": 20,
            "sub_fields": [
                {
                    "key": "field_693ab6f7dc154",
                    "label": "stat_number",
                    "name": "stat_number",
                    "aria-label": "",
                    "type": "number",
                    "instructions": "",
                    "required": 0,
                    "conditional_logic": 0,
                    "wrapper": {
                        "width": "",
                        "class": "",
                        "id": ""
                    },
                    "default_value": "",
                    "min": "",
                    "max": "",
                    "allow_in_bindings": 0,
                    "placeholder": "",
                    "step": "",
                    "prepend": "",
                    "append": "",
                    "parent_repeater": "field_693ab6f1dc153"
                },
                {
                    "key": "field_693ab707dc155",
                    "label": "stat_suffix",
                    "name": "stat_suffix",
                    "aria-label": "",
                    "type": "text",
                    "instructions": "",
                    "required": 0,
                    "conditional_logic": 0,
                    "wrapper": {
                        "width": "",
                        "class": "",
                        "id": ""
                    },
                    "default_value": "",
                    "maxlength": "",
                    "allow_in_bindings": 0,
                    "placeholder": "",
                    "prepend": "",
                    "append": "",
                    "parent_repeater": "field_693ab6f1dc153"
                },
                {
                    "key": "field_693ab70bdc156",
                    "label": "stat_label",
                    "name": "stat_label",
                    "aria-label": "",
                    "type": "text",
                    "instructions": "",
                    "required": 0,
                    "conditional_logic": 0,
                    "wrapper": {
                        "width": "",
                        "class": "",
                        "id": ""
                    },
                    "default_value": "",
                    "maxlength": "",
                    "allow_in_bindings": 0,
                    "placeholder": "",
                    "prepend": "",
                    "append": "",
                    "parent_repeater": "field_693ab6f1dc153"
                }
            ]
        },
        {
            "key": "field_693ab716dc157",
            "label": "Case Studies",
            "name": "",
            "aria-label": "",
            "type": "tab",
            "instructions": "",
            "required": 0,
            "conditional_logic": 0,
            "wrapper": {
                "width": "",
                "class": "",
                "id": ""
            },
            "placement": "top",
            "endpoint": 0,
            "selected": 0
        },
        {
            "key": "field_693ab779dc158",
            "label": "casestudies_featured_label",
            "name": "casestudies_featured_label",
            "aria-label": "",
            "type": "text",
            "instructions": "",
            "required": 0,
            "conditional_logic": 0,
            "wrapper": {
                "width": "",
                "class": "",
                "id": ""
            },
            "default_value": "",
            "maxlength": "",
            "allow_in_bindings": 0,
            "placeholder": "",
            "prepend": "",
            "append": ""
        },
        {
            "key": "field_693ab78cdc159",
            "label": "casestudies_featured_heading",
            "name": "casestudies_featured_heading",
            "aria-label": "",
            "type": "wysiwyg",
            "instructions": "",
            "required": 0,
            "conditional_logic": 0,
            "wrapper": {
                "width": "",
                "class": "",
                "id": ""
            },
            "default_value": "",
            "allow_in_bindings": 0,
            "tabs": "all",
            "toolbar": "full",
            "media_upload": 1,
            "delay": 0
        },
        {
            "key": "field_693ab794dc15a",
            "label": "casestudies_featured_subheading",
            "name": "casestudies_featured_subheading",
            "aria-label": "",
            "type": "wysiwyg",
            "instructions": "",
            "required": 0,
            "conditional_logic": 0,
            "wrapper": {
                "width": "",
                "class": "",
                "id": ""
            },
            "default_value": "",
            "allow_in_bindings": 0,
            "tabs": "all",
            "toolbar": "full",
            "media_upload": 1,
            "delay": 0
        },
        {
            "key": "field_693ab7afdc15b",
            "label": "casestudies_featured_items",
            "name": "casestudies_featured_items",
            "aria-label": "",
            "type": "repeater",
            "instructions": "",
            "required": 0,
            "conditional_logic": 0,
            "wrapper": {
                "width": "",
                "class": "",
                "id": ""
            },
            "layout": "table",
            "pagination": 0,
            "min": 0,
            "max": 0,
            "collapsed": "",
            "button_label": "Add Row",
            "rows_per_page": 20,
            "sub_fields": [
                {
                    "key": "field_693ab7b8dc15c",
                    "label": "image",
                    "name": "image",
                    "aria-label": "",
                    "type": "image",
                    "instructions": "",
                    "required": 0,
                    "conditional_logic": 0,
                    "wrapper": {
                        "width": "",
                        "class": "",
                        "id": ""
                    },
                    "return_format": "array",
                    "library": "all",
                    "min_width": "",
                    "min_height": "",
                    "min_size": "",
                    "max_width": "",
                    "max_height": "",
                    "max_size": "",
                    "mime_types": "",
                    "allow_in_bindings": 0,
                    "preview_size": "medium",
                    "parent_repeater": "field_693ab7afdc15b"
                },
                {
                    "key": "field_693ab7bedc15d",
                    "label": "client_name",
                    "name": "client_name",
                    "aria-label": "",
                    "type": "text",
                    "instructions": "",
                    "required": 0,
                    "conditional_logic": 0,
                    "wrapper": {
                        "width": "",
                        "class": "",
                        "id": ""
                    },
                    "default_value": "",
                    "maxlength": "",
                    "allow_in_bindings": 0,
                    "placeholder": "",
                    "prepend": "",
                    "append": "",
                    "parent_repeater": "field_693ab7afdc15b"
                },
                {
                    "key": "field_693ab7c8dc15e",
                    "label": "industry",
                    "name": "industry",
                    "aria-label": "",
                    "type": "text",
                    "instructions": "",
                    "required": 0,
                    "conditional_logic": 0,
                    "wrapper": {
                        "width": "",
                        "class": "",
                        "id": ""
                    },
                    "default_value": "",
                    "maxlength": "",
                    "allow_in_bindings": 0,
                    "placeholder": "",
                    "prepend": "",
                    "append": "",
                    "parent_repeater": "field_693ab7afdc15b"
                },
                {
                    "key": "field_693ab7cbdc15f",
                    "label": "description",
                    "name": "description",
                    "aria-label": "",
                    "type": "wysiwyg",
                    "instructions": "",
                    "required": 0,
                    "conditional_logic": 0,
                    "wrapper": {
                        "width": "",
                        "class": "",
                        "id": ""
                    },
                    "default_value": "",
                    "allow_in_bindings": 0,
                    "tabs": "all",
                    "toolbar": "full",
                    "media_upload": 1,
                    "delay": 0,
                    "parent_repeater": "field_693ab7afdc15b"
                },
                {
                    "key": "field_693ab7d3dc160",
                    "label": "stat_1_number",
                    "name": "stat_1_number",
                    "aria-label": "",
                    "type": "text",
                    "instructions": "",
                    "required": 0,
                    "conditional_logic": 0,
                    "wrapper": {
                        "width": "",
                        "class": "",
                        "id": ""
                    },
                    "default_value": "",
                    "maxlength": "",
                    "allow_in_bindings": 0,
                    "placeholder": "",
                    "prepend": "",
                    "append": "",
                    "parent_repeater": "field_693ab7afdc15b"
                },
                {
                    "key": "field_693ab7dadc161",
                    "label": "stat_1_label",
                    "name": "stat_1_label",
                    "aria-label": "",
                    "type": "text",
                    "instructions": "",
                    "required": 0,
                    "conditional_logic": 0,
                    "wrapper": {
                        "width": "",
                        "class": "",
                        "id": ""
                    },
                    "default_value": "",
                    "maxlength": "",
                    "allow_in_bindings": 0,
                    "placeholder": "",
                    "prepend": "",
                    "append": "",
                    "parent_repeater": "field_693ab7afdc15b"
                },
                {
                    "key": "field_693ab7e1dc162",
                    "label": "stat_2_number",
                    "name": "stat_2_number",
                    "aria-label": "",
                    "type": "text",
                    "instructions": "",
                    "required": 0,
                    "conditional_logic": 0,
                    "wrapper": {
                        "width": "",
                        "class": "",
                        "id": ""
                    },
                    "default_value": "",
                    "maxlength": "",
                    "allow_in_bindings": 0,
                    "placeholder": "",
                    "prepend": "",
                    "append": "",
                    "parent_repeater": "field_693ab7afdc15b"
                },
                {
                    "key": "field_693ab7e7dc163",
                    "label": "stat_2_label",
                    "name": "stat_2_label",
                    "aria-label": "",
                    "type": "text",
                    "instructions": "",
                    "required": 0,
                    "conditional_logic": 0,
                    "wrapper": {
                        "width": "",
                        "class": "",
                        "id": ""
                    },
                    "default_value": "",
                    "maxlength": "",
                    "allow_in_bindings": 0,
                    "placeholder": "",
                    "prepend": "",
                    "append": "",
                    "parent_repeater": "field_693ab7afdc15b"
                },
                {
                    "key": "field_693ab7eedc164",
                    "label": "case_study_link",
                    "name": "case_study_link",
                    "aria-label": "",
                    "type": "link",
                    "instructions": "",
                    "required": 0,
                    "conditional_logic": 0,
                    "wrapper": {
                        "width": "",
                        "class": "",
                        "id": ""
                    },
                    "return_format": "array",
                    "allow_in_bindings": 0,
                    "parent_repeater": "field_693ab7afdc15b"
                }
            ]
        },
        {
            "key": "field_693ab816ca926",
            "label": "All Case Studies",
            "name": "",
            "aria-label": "",
            "type": "tab",
            "instructions": "",
            "required": 0,
            "conditional_logic": 0,
            "wrapper": {
                "width": "",
                "class": "",
                "id": ""
            },
            "placement": "top",
            "endpoint": 0,
            "selected": 0
        },
        {
            "key": "field_693ab81dca927",
            "label": "casestudies_all_label",
            "name": "casestudies_all_label",
            "aria-label": "",
            "type": "text",
            "instructions": "",
            "required": 0,
            "conditional_logic": 0,
            "wrapper": {
                "width": "",
                "class": "",
                "id": ""
            },
            "default_value": "",
            "maxlength": "",
            "allow_in_bindings": 0,
            "placeholder": "",
            "prepend": "",
            "append": ""
        },
        {
            "key": "field_693ab823ca928",
            "label": "casestudies_all_heading",
            "name": "casestudies_all_heading",
            "aria-label": "",
            "type": "wysiwyg",
            "instructions": "",
            "required": 0,
            "conditional_logic": 0,
            "wrapper": {
                "width": "",
                "class": "",
                "id": ""
            },
            "default_value": "",
            "allow_in_bindings": 0,
            "tabs": "all",
            "toolbar": "full",
            "media_upload": 1,
            "delay": 0
        },
        {
            "key": "field_693ab829ca929",
            "label": "casestudies_all_subheading",
            "name": "casestudies_all_subheading",
            "aria-label": "",
            "type": "wysiwyg",
            "instructions": "",
            "required": 0,
            "conditional_logic": 0,
            "wrapper": {
                "width": "",
                "class": "",
                "id": ""
            },
            "default_value": "",
            "allow_in_bindings": 0,
            "tabs": "all",
            "toolbar": "full",
            "media_upload": 1,
            "delay": 0
        },
        {
            "key": "field_693ab830ca92a",
            "label": "casestudies_all_items",
            "name": "casestudies_all_items",
            "aria-label": "",
            "type": "repeater",
            "instructions": "",
            "required": 0,
            "conditional_logic": 0,
            "wrapper": {
                "width": "",
                "class": "",
                "id": ""
            },
            "layout": "table",
            "pagination": 0,
            "min": 0,
            "max": 0,
            "collapsed": "",
            "button_label": "Add Row",
            "rows_per_page": 20,
            "sub_fields": [
                {
                    "key": "field_693ab83cca92b",
                    "label": "Image",
                    "name": "image",
                    "aria-label": "",
                    "type": "image",
                    "instructions": "",
                    "required": 0,
                    "conditional_logic": 0,
                    "wrapper": {
                        "width": "",
                        "class": "",
                        "id": ""
                    },
                    "return_format": "array",
                    "library": "all",
                    "min_width": "",
                    "min_height": "",
                    "min_size": "",
                    "max_width": "",
                    "max_height": "",
                    "max_size": "",
                    "mime_types": "",
                    "allow_in_bindings": 0,
                    "preview_size": "medium",
                    "parent_repeater": "field_693ab830ca92a"
                },
                {
                    "key": "field_693ab842ca92c",
                    "label": "client_name",
                    "name": "client_name",
                    "aria-label": "",
                    "type": "text",
                    "instructions": "",
                    "required": 0,
                    "conditional_logic": 0,
                    "wrapper": {
                        "width": "",
                        "class": "",
                        "id": ""
                    },
                    "default_value": "",
                    "maxlength": "",
                    "allow_in_bindings": 0,
                    "placeholder": "",
                    "prepend": "",
                    "append": "",
                    "parent_repeater": "field_693ab830ca92a"
                },
                {
                    "key": "field_693ab849ca92d",
                    "label": "services",
                    "name": "services",
                    "aria-label": "",
                    "type": "text",
                    "instructions": "",
                    "required": 0,
                    "conditional_logic": 0,
                    "wrapper": {
                        "width": "",
                        "class": "",
                        "id": ""
                    },
                    "default_value": "",
                    "maxlength": "",
                    "allow_in_bindings": 0,
                    "placeholder": "",
                    "prepend": "",
                    "append": "",
                    "parent_repeater": "field_693ab830ca92a"
                },
                {
                    "key": "field_693ab84eca92e",
                    "label": "case_study_link",
                    "name": "case_study_link",
                    "aria-label": "",
                    "type": "link",
                    "instructions": "",
                    "required": 0,
                    "conditional_logic": 0,
                    "wrapper": {
                        "width": "",
                        "class": "",
                        "id": ""
                    },
                    "return_format": "array",
                    "allow_in_bindings": 0,
                    "parent_repeater": "field_693ab830ca92a"
                }
            ]
        },
        {
            "key": "field_693ab85980db3",
            "label": "Clients",
            "name": "",
            "aria-label": "",
            "type": "tab",
            "instructions": "",
            "required": 0,
            "conditional_logic": 0,
            "wrapper": {
                "width": "",
                "class": "",
                "id": ""
            },
            "placement": "top",
            "endpoint": 0,
            "selected": 0
        },
        {
            "key": "field_693ab86280db4",
            "label": "casestudies_clients_label",
            "name": "casestudies_clients_label",
            "aria-label": "",
            "type": "text",
            "instructions": "",
            "required": 0,
            "conditional_logic": 0,
            "wrapper": {
                "width": "",
                "class": "",
                "id": ""
            },
            "default_value": "",
            "maxlength": "",
            "allow_in_bindings": 0,
            "placeholder": "",
            "prepend": "",
            "append": ""
        },
        {
            "key": "field_693ab86880db5",
            "label": "casestudies_clients_heading",
            "name": "casestudies_clients_heading",
            "aria-label": "",
            "type": "wysiwyg",
            "instructions": "",
            "required": 0,
            "conditional_logic": 0,
            "wrapper": {
                "width": "",
                "class": "",
                "id": ""
            },
            "default_value": "",
            "allow_in_bindings": 0,
            "tabs": "all",
            "toolbar": "full",
            "media_upload": 1,
            "delay": 0
        },
        {
            "key": "field_693ab87080db6",
            "label": "casestudies_clients_logos",
            "name": "casestudies_clients_logos",
            "aria-label": "",
            "type": "repeater",
            "instructions": "",
            "required": 0,
            "conditional_logic": 0,
            "wrapper": {
                "width": "",
                "class": "",
                "id": ""
            },
            "layout": "table",
            "pagination": 0,
            "min": 0,
            "max": 0,
            "collapsed": "",
            "button_label": "Add Row",
            "rows_per_page": 20,
            "sub_fields": [
                {
                    "key": "field_693ab87e80db7",
                    "label": "logo",
                    "name": "logo",
                    "aria-label": "",
                    "type": "image",
                    "instructions": "",
                    "required": 0,
                    "conditional_logic": 0,
                    "wrapper": {
                        "width": "",
                        "class": "",
                        "id": ""
                    },
                    "return_format": "array",
                    "library": "all",
                    "min_width": "",
                    "min_height": "",
                    "min_size": "",
                    "max_width": "",
                    "max_height": "",
                    "max_size": "",
                    "mime_types": "",
                    "allow_in_bindings": 0,
                    "preview_size": "medium",
                    "parent_repeater": "field_693ab87080db6"
                }
            ]
        }
    ],
    "location": [
        [
            {
                "param": "page",
                "operator": "==",
                "value": "1828"
            }
        ]
    ],
    "menu_order": 0,
    "position": "normal",
    "style": "default",
    "label_placement": "top",
    "instruction_placement": "label",
    "hide_on_screen": "",
    "active": true,
    "description": "",
    "show_in_rest": 0,
    "display_title": "",
    "modified": 1765456005
}
